{
  "title": "16-inch MacBook Pro - Space Grey",
  "image": "https://jsonformatter.org/img/tom-cruise.jpg",
  "details": [
    {
      "component": "Processor",
      "title": "2.3GHz 8-core 9th-generation Intel Core i9 processor, Turbo Boost up to 4.8GHz",
      "cost": "0",
      "selected":true
    },
    {
      "component": "Processor",
      "title": "2.4GHz 8-core 9th-generation Intel Core i9 processor, Turbo Boost up to 5.0GHz",
      "cost": "20,000",
      "selected":false
    },
    {
      "component": "Memory",
      "title": "16GB 2666MHz DDR4 memory",
      "cost": "0",
      "selected":true
    },
    {
      "component": "Memory",
      "title": "32GB 2666MHz DDR4 memory",
      "selected":false,
      "cost": "40,000"
    },
    {
      "component": "Memory",
      "title": "64GB 2666MHz DDR4 memory",
      "selected":false,
      "cost": "80,000"
    },
    {
      "component": "Graphics",
      "title": "AMD Radeon Pro 5500M with 4GB of GDDR6 memory",
      "cost": "0",
      "selected":true
    },
    {
      "component": "Graphics",
      "title": "AMD Radeon Pro 5500M with 8GB of GDDR6 memory",
      "selected":false,
      "cost": "10,000"
    },
    {
      "component": "Graphics",
      "title": "AMD Radeon Pro 5600M with 8GB of HBM2 memory",
      "selected":false,
      "cost": "70,000"
    },
    {
      "component": "Storage",
      "title": "1TB SSD storage",
      "cost": "0",
      "selected":true
    },
    {
      "component": "Storage",
      "title": "2TB SSD storage",
      "selected":false,
      "cost": "40,000"
    },
    {
      "component": "Storage",
      "title": "4TB SSD storage",
      "selected":false,
      "cost": "100,000"
    },
    {
      "component": "Storage",
      "title": "8TB SSD storage",
      "selected":false,
      "cost": "220,000"
    }
  ]
}
